whatsclientpy/__init__.py
whatsclientpy/buttons.py
whatsclientpy/client.py
whatsclientpy/events.py
whatsclientpy/header.py
whatsclientpy/header_type.py
whatsclientpy/list.py
whatsclientpy/msg.py
whatsclientpy/msgtypes.py
whatsclientpy/on_message.py
whatsclientpy/send.py
whatsclientpy-1.2.dist-info/METADATA
whatsclientpy-1.2.dist-info/WHEEL
whatsclientpy-1.2.dist-info/top_level.txt
whatsclientpy-1.2.dist-info/RECORD
